apps/__init__.py
apps/app1.py
apps/app2.py
apps/fourohfour.py
apps/homepage.py
turbo_dash/__init__.py
turbo_dash/_helpers.py
turbo_dash/_lookups.py
turbo_dash/_turbo_dashboard.py
turbo_dash/_turbo_dashboard_page.py
turbo_dash/_turbo_filter.py
turbo_dash/_turbo_output.py
turbo_dash/dashboard_components.py
turbo_dash/inputs.py
turbo_dash/outputs.py
turbo_dash/data/__init__.py
turbo_dash/package_data/datasets/gapminder.csv.gz
turbo_dash-0.5.0.dist-info/LICENSE
turbo_dash-0.5.0.dist-info/METADATA
turbo_dash-0.5.0.dist-info/WHEEL
turbo_dash-0.5.0.dist-info/top_level.txt
turbo_dash-0.5.0.dist-info/RECORD
